{
  "job_id": "f5ac2d44ca3644cf8cd10ec148304129",
  "filename": "NMMC_812.pdf",
  "total_pages": 1,
  "marathi_measurements": {},
  "english_measurements": {
    "organization": "Navi Mumbai Municipal Corporation",
    "address": "1st Floor, Belapur Bhavan, C.B.D., Navi Mumbai - 400 614",
    "phone_numbers": [
      "757 17 33",
      "757 17 28",
      "757 40 22"
    ],
    "fax_no": "757 37 85",
    "document_number": "NMMC/Pari-1/T.C.No.-10/1182/2025",
    "dn_number": "10/1182/2025",
    "date": "3/10/2025",
    "salutation": "To,",
    "recipient_name": "M/s. Bharti Airtel Ltd.",
    "recipient_address": "7th Floor, Interface-7, New Link Road, Malad (W)",
    "subject": "Regarding payment of road excavation charges.",
    "reference_1": "1. Your organization's letter dated 14/7/25.",
    "reference_2": "2. Estimate submitted by the Executive Engineer, Turbhe on 23/9/25.",
    "introduction": "This is to inform you that M/s. Bharti Airtel Limited has proposed excavation work for a total of 812 meters using the open trenching method from near HP Petrol Pump to Manish Export in the South Central Nerul division. In this regard, the Hon. Executive Engineer has submitted an estimate for the asphalt road excavation.",
    "instructions": "As per the government resolution and the estimate provided by the Executive Engineer, the charges are shown. Therefore, you are requested to deposit the following amount for the excavation work in the Municipal Corporation.",
    "conclusion": "As per the above, the total amount of Rs. 1,58,31,241/- (in words: Rupees One Crore Fifty-Eight Lakh Thirty-One Thousand Two Hundred Forty-One only) should be submitted to the accounts department of Navi Mumbai Municipal Corporation through a demand draft (D.D.). After which, permission for road excavation will be granted to your organization. Please note this. It will be the responsibility of your organization to pay GST on the above amount as per Notification No. 03/2018 Central Tax (Rate) dated 25 January 2018.",
    "title": "HDD/Open Trench",
    "line_items": [
      {
        "sr_no": "1",
        "surface_type": "New asphalt surface",
        "no_of_pits": 8.0,
        "length_m": 1.5,
        "width_m": 1.5,
        "area_sqm": 18.0,
        "rate_per_sqm": 9600.0,
        "amount": 172800.0
      },
      {
        "sr_no": null,
        "surface_type": "Cable through duct",
        "no_of_pits": 0.0,
        "length_m": 0.0,
        "width_m": 0.0,
        "area_sqm": 0.0,
        "rate_per_sqm": 0.0,
        "amount": 0.0
      },
      {
        "sr_no": null,
        "surface_type": "No. of ducts 3",
        "no_of_pits": null,
        "length_m": 0.0,
        "width_m": 0.0,
        "area_sqm": 812.0,
        "rate_per_sqm": null,
        "amount": 2436.0
      },
      {
        "sr_no": "1",
        "surface_type": "New asphalt surface (Open trench method)",
        "no_of_pits": 0.0,
        "length_m": 0.0,
        "width_m": 0.0,
        "area_sqm": 627.0,
        "rate_per_sqm": 9600.0,
        "amount": 6019200.0
      }
    ],
    "total_area_sqm": 812.0,
    "charges_summary": [
      {
        "code": "A",
        "description": "Reinstatement Charges",
        "amount": 12386436.0
      },
      {
        "code": "B",
        "description": "Supervision charges on A @ 15%",
        "amount": 1857965.0
      },
      {
        "code": "C",
        "description": "Security deposit on A+B @ 10%",
        "amount": 1424440.0
      },
      {
        "code": "D",
        "description": "Ground rent at the rate of Rs 10/- per year per meter for 20 years as a lump sum of Rs 200/- per meter",
        "amount": 162400.0
      }
    ],
    "total_amount": 15831241.0,
    "supervision_charges": 1857965.0,
    "ground_rent": 162400.0,
    "gst_number": "27AAALC0296J1Z4",
    "pan_number": "AAALC0296J",
    "service_no": "997212",
    "length_m": 1.5,
    "width_m": 1.5,
    "area_sqm": 18.0,
    "name": "Somnath Potare",
    "designation": "Deputy Commissioner (Zone-1)",
    "amount": "10"
  },
  "table_rows": [
    {
      "sr_no": "1",
      "type/description": "नविन डांबरी पृष्ठभाग",
      "quantity/pits": 8.0,
      "length": 1.5,
      "width": 1.5,
      "area": 18.0,
      "rate": 9600.0,
      "amount": 172800.0
    },
    {
      "sr_no": null,
      "type/description": "डक्ट मधुन केबल",
      "quantity/pits": 0.0,
      "length": 0.0,
      "width": 0.0,
      "area": 0.0,
      "rate": 0.0,
      "amount": 0.0
    },
    {
      "sr_no": null,
      "type/description": "डक्ट ची संख्या 3",
      "quantity/pits": null,
      "length": null,
      "width": 0.0,
      "area": 812.0,
      "rate": 0.0,
      "amount": 2436.0
    },
    {
      "sr_no": "1",
      "type/description": "नविन डांबरी पृष्ठभाग (ओपन ट्रेंच पध्दत)",
      "quantity/pits": 0.0,
      "length": 0.0,
      "width": 0.0,
      "area": 627.0,
      "rate": 9600.0,
      "amount": 6019200.0
    },
    {
      "sr_no": null,
      "type/description": "एकूण चौ.मी.",
      "quantity/pits": null,
      "length": null,
      "width": null,
      "area": null,
      "rate": null,
      "amount": 812.0
    },
    {
      "sr_no": "A)",
      "type/description": "पुर्न:स्थापना शुल्क",
      "quantity/pits": null,
      "length": null,
      "width": null,
      "area": null,
      "rate": null,
      "amount": 12386436
    },
    {
      "sr_no": "B)",
      "type/description": "A वर पर्यवेक्षण शुल्क १५ %",
      "quantity/pits": null,
      "length": null,
      "width": null,
      "area": null,
      "rate": null,
      "amount": 1857965
    },
    {
      "sr_no": "C)",
      "type/description": "A+B वर सुरक्षा अनामत रक्कम १०%",
      "quantity/pits": null,
      "length": null,
      "width": null,
      "area": null,
      "rate": null,
      "amount": 1424440
    },
    {
      "sr_no": "D)",
      "type/description": "रु 10/- प्रति वर्ष प्रति मीटर या प्रमाणे 20 वर्षासाठी एकरक्कमी रु200/- प्रती मीटर प्रमाणे भुईभाडे",
      "quantity/pits": null,
      "length": null,
      "width": null,
      "area": null,
      "rate": null,
      "amount": 162400
    },
    {
      "sr_no": null,
      "type/description": "एकूण",
      "quantity/pits": null,
      "length": null,
      "width": null,
      "area": null,
      "rate": null,
      "amount": 15831241.0
    },
    {
      "sr_no": "1",
      "type/description": "नविन डांबरी पृष्ठभाग",
      "quantity/pits": 8.0,
      "length": 1.5,
      "width": 1.5,
      "area": 18.0,
      "rate": 9600.0,
      "amount": 172800.0
    },
    {
      "sr_no": null,
      "type/description": "डक्ट मधुन केबल",
      "quantity/pits": 0.0,
      "length": 0.0,
      "width": 0.0,
      "area": 0.0,
      "rate": 0.0,
      "amount": 0.0
    },
    {
      "sr_no": null,
      "type/description": "डक्ट ची संख्या 3",
      "quantity/pits": 0.0,
      "length": null,
      "width": null,
      "area": 812.0,
      "rate": 0.0,
      "amount": 2436.0
    },
    {
      "sr_no": "1",
      "type/description": "नविन डांबरी पृष्ठभाग (ओपन ट्रेंच पध्दत)",
      "quantity/pits": 0.0,
      "length": 0.0,
      "width": 0.0,
      "area": 627.0,
      "rate": 9600.0,
      "amount": 6019200.0
    },
    {
      "sr_no": null,
      "type/description": "पुनःस्थापना शुल्क",
      "quantity/pits": null,
      "length": null,
      "width": null,
      "area": null,
      "rate": null,
      "amount": 12386436.0
    },
    {
      "sr_no": "A",
      "type/description": "A वर पर्यवेक्षण शुल्क १५ %",
      "quantity/pits": null,
      "length": null,
      "width": null,
      "area": null,
      "rate": null,
      "amount": 1857965.0
    },
    {
      "sr_no": "B",
      "type/description": "A+B वर सुरक्षा अनामत रक्कम १०%",
      "quantity/pits": null,
      "length": null,
      "width": null,
      "area": null,
      "rate": null,
      "amount": 1424440.0
    },
    {
      "sr_no": "D",
      "type/description": "रु १०/- प्रति वर्ष प्रति मीटर या प्रमाणे 20 वर्षासाठी एकरक्कमी रु200/- प्रती मीटर प्रमाणे भुईभाडे",
      "quantity/pits": null,
      "length": null,
      "width": null,
      "area": null,
      "rate": null,
      "amount": 162400.0
    },
    {
      "sr_no": null,
      "type/description": "एकूण",
      "quantity/pits": null,
      "length": null,
      "width": null,
      "area": null,
      "rate": null,
      "amount": 15831241.0
    }
  ],
  "summary": {},
  "extracted_measurements": {
    "organization": "Navi Mumbai Municipal Corporation",
    "address": "1st Floor, Belapur Bhavan, C.B.D., Navi Mumbai - 400 614",
    "phone_numbers": [
      "757 17 33",
      "757 17 28",
      "757 40 22"
    ],
    "fax_no": "757 37 85",
    "document_number": "NMMC/Pari-1/T.C.No.-10/1182/2025",
    "dn_number": "10/1182/2025",
    "date": "3/10/2025",
    "salutation": "To,",
    "recipient_name": "M/s. Bharti Airtel Ltd.",
    "recipient_address": "7th Floor, Interface-7, New Link Road, Malad (W)",
    "subject": "Regarding payment of road excavation charges.",
    "reference_1": "1. Your organization's letter dated 14/7/25.",
    "reference_2": "2. Estimate submitted by the Executive Engineer, Turbhe on 23/9/25.",
    "introduction": "This is to inform you that M/s. Bharti Airtel Limited has proposed excavation work for a total of 812 meters using the open trenching method from near HP Petrol Pump to Manish Export in the South Central Nerul division. In this regard, the Hon. Executive Engineer has submitted an estimate for the asphalt road excavation.",
    "instructions": "As per the government resolution and the estimate provided by the Executive Engineer, the charges are shown. Therefore, you are requested to deposit the following amount for the excavation work in the Municipal Corporation.",
    "conclusion": "As per the above, the total amount of Rs. 1,58,31,241/- (in words: Rupees One Crore Fifty-Eight Lakh Thirty-One Thousand Two Hundred Forty-One only) should be submitted to the accounts department of Navi Mumbai Municipal Corporation through a demand draft (D.D.). After which, permission for road excavation will be granted to your organization. Please note this. It will be the responsibility of your organization to pay GST on the above amount as per Notification No. 03/2018 Central Tax (Rate) dated 25 January 2018.",
    "title": "HDD/Open Trench",
    "line_items": [
      {
        "sr_no": "1",
        "surface_type": "New asphalt surface",
        "no_of_pits": 8.0,
        "length_m": 1.5,
        "width_m": 1.5,
        "area_sqm": 18.0,
        "rate_per_sqm": 9600.0,
        "amount": 172800.0
      },
      {
        "sr_no": null,
        "surface_type": "Cable through duct",
        "no_of_pits": 0.0,
        "length_m": 0.0,
        "width_m": 0.0,
        "area_sqm": 0.0,
        "rate_per_sqm": 0.0,
        "amount": 0.0
      },
      {
        "sr_no": null,
        "surface_type": "No. of ducts 3",
        "no_of_pits": null,
        "length_m": 0.0,
        "width_m": 0.0,
        "area_sqm": 812.0,
        "rate_per_sqm": null,
        "amount": 2436.0
      },
      {
        "sr_no": "1",
        "surface_type": "New asphalt surface (Open trench method)",
        "no_of_pits": 0.0,
        "length_m": 0.0,
        "width_m": 0.0,
        "area_sqm": 627.0,
        "rate_per_sqm": 9600.0,
        "amount": 6019200.0
      }
    ],
    "total_area_sqm": 812.0,
    "charges_summary": [
      {
        "code": "A",
        "description": "Reinstatement Charges",
        "amount": 12386436.0
      },
      {
        "code": "B",
        "description": "Supervision charges on A @ 15%",
        "amount": 1857965.0
      },
      {
        "code": "C",
        "description": "Security deposit on A+B @ 10%",
        "amount": 1424440.0
      },
      {
        "code": "D",
        "description": "Ground rent at the rate of Rs 10/- per year per meter for 20 years as a lump sum of Rs 200/- per meter",
        "amount": 162400.0
      }
    ],
    "total_amount": 15831241.0,
    "supervision_charges": 1857965.0,
    "ground_rent": 162400.0,
    "gst_number": "27AAALC0296J1Z4",
    "pan_number": "AAALC0296J",
    "service_no": "997212",
    "length_m": 1.5,
    "width_m": 1.5,
    "area_sqm": 18.0,
    "name": "Somnath Potare",
    "designation": "Deputy Commissioner (Zone-1)",
    "amount": "10"
  },
  "page_wise_measurements": [
    {
      "page_number": 1,
      "marathi": {},
      "english": {
        "organization": "Navi Mumbai Municipal Corporation",
        "address": "1st Floor, Belapur Bhavan, C.B.D., Navi Mumbai - 400 614",
        "phone_numbers": [
          "757 17 33",
          "757 17 28",
          "757 40 22"
        ],
        "fax_no": "757 37 85",
        "document_number": "NMMC/Pari-1/T.C.No.-10/1182/2025",
        "dn_number": "10/1182/2025",
        "date": "3/10/2025",
        "salutation": "To,",
        "recipient_name": "M/s. Bharti Airtel Ltd.",
        "recipient_address": "7th Floor, Interface-7, New Link Road, Malad (W)",
        "subject": "Regarding payment of road excavation charges.",
        "reference_1": "1. Your organization's letter dated 14/7/25.",
        "reference_2": "2. Estimate submitted by the Executive Engineer, Turbhe on 23/9/25.",
        "introduction": "This is to inform you that M/s. Bharti Airtel Limited has proposed excavation work for a total of 812 meters using the open trenching method from near HP Petrol Pump to Manish Export in the South Central Nerul division. In this regard, the Hon. Executive Engineer has submitted an estimate for the asphalt road excavation.",
        "instructions": "As per the government resolution and the estimate provided by the Executive Engineer, the charges are shown. Therefore, you are requested to deposit the following amount for the excavation work in the Municipal Corporation.",
        "conclusion": "As per the above, the total amount of Rs. 1,58,31,241/- (in words: Rupees One Crore Fifty-Eight Lakh Thirty-One Thousand Two Hundred Forty-One only) should be submitted to the accounts department of Navi Mumbai Municipal Corporation through a demand draft (D.D.). After which, permission for road excavation will be granted to your organization. Please note this. It will be the responsibility of your organization to pay GST on the above amount as per Notification No. 03/2018 Central Tax (Rate) dated 25 January 2018.",
        "title": "HDD/Open Trench",
        "line_items": [
          {
            "sr_no": "1",
            "surface_type": "New asphalt surface",
            "no_of_pits": 8.0,
            "length_m": 1.5,
            "width_m": 1.5,
            "area_sqm": 18.0,
            "rate_per_sqm": 9600.0,
            "amount": 172800.0
          },
          {
            "sr_no": null,
            "surface_type": "Cable through duct",
            "no_of_pits": 0.0,
            "length_m": 0.0,
            "width_m": 0.0,
            "area_sqm": 0.0,
            "rate_per_sqm": 0.0,
            "amount": 0.0
          },
          {
            "sr_no": null,
            "surface_type": "No. of ducts 3",
            "no_of_pits": null,
            "length_m": 0.0,
            "width_m": 0.0,
            "area_sqm": 812.0,
            "rate_per_sqm": null,
            "amount": 2436.0
          },
          {
            "sr_no": "1",
            "surface_type": "New asphalt surface (Open trench method)",
            "no_of_pits": 0.0,
            "length_m": 0.0,
            "width_m": 0.0,
            "area_sqm": 627.0,
            "rate_per_sqm": 9600.0,
            "amount": 6019200.0
          }
        ],
        "total_area_sqm": 812.0,
        "charges_summary": [
          {
            "code": "A",
            "description": "Reinstatement Charges",
            "amount": 12386436.0
          },
          {
            "code": "B",
            "description": "Supervision charges on A @ 15%",
            "amount": 1857965.0
          },
          {
            "code": "C",
            "description": "Security deposit on A+B @ 10%",
            "amount": 1424440.0
          },
          {
            "code": "D",
            "description": "Ground rent at the rate of Rs 10/- per year per meter for 20 years as a lump sum of Rs 200/- per meter",
            "amount": 162400.0
          }
        ],
        "total_amount": 15831241.0,
        "supervision_charges": 1857965.0,
        "ground_rent": 162400.0,
        "gst_number": "27AAALC0296J1Z4",
        "pan_number": "AAALC0296J",
        "service_no": "997212",
        "length_m": 1.5,
        "width_m": 1.5,
        "area_sqm": 18.0,
        "name": "Somnath Potare",
        "designation": "Deputy Commissioner (Zone-1)",
        "amount": "10"
      },
      "table_rows": [
        {
          "sr_no": "1",
          "type/description": "नविन डांबरी पृष्ठभाग",
          "quantity/pits": 8.0,
          "length": 1.5,
          "width": 1.5,
          "area": 18.0,
          "rate": 9600.0,
          "amount": 172800.0
        },
        {
          "sr_no": null,
          "type/description": "डक्ट मधुन केबल",
          "quantity/pits": 0.0,
          "length": 0.0,
          "width": 0.0,
          "area": 0.0,
          "rate": 0.0,
          "amount": 0.0
        },
        {
          "sr_no": null,
          "type/description": "डक्ट ची संख्या 3",
          "quantity/pits": null,
          "length": null,
          "width": 0.0,
          "area": 812.0,
          "rate": 0.0,
          "amount": 2436.0
        },
        {
          "sr_no": "1",
          "type/description": "नविन डांबरी पृष्ठभाग (ओपन ट्रेंच पध्दत)",
          "quantity/pits": 0.0,
          "length": 0.0,
          "width": 0.0,
          "area": 627.0,
          "rate": 9600.0,
          "amount": 6019200.0
        },
        {
          "sr_no": null,
          "type/description": "एकूण चौ.मी.",
          "quantity/pits": null,
          "length": null,
          "width": null,
          "area": null,
          "rate": null,
          "amount": 812.0
        },
        {
          "sr_no": "A)",
          "type/description": "पुर्न:स्थापना शुल्क",
          "quantity/pits": null,
          "length": null,
          "width": null,
          "area": null,
          "rate": null,
          "amount": 12386436
        },
        {
          "sr_no": "B)",
          "type/description": "A वर पर्यवेक्षण शुल्क १५ %",
          "quantity/pits": null,
          "length": null,
          "width": null,
          "area": null,
          "rate": null,
          "amount": 1857965
        },
        {
          "sr_no": "C)",
          "type/description": "A+B वर सुरक्षा अनामत रक्कम १०%",
          "quantity/pits": null,
          "length": null,
          "width": null,
          "area": null,
          "rate": null,
          "amount": 1424440
        },
        {
          "sr_no": "D)",
          "type/description": "रु 10/- प्रति वर्ष प्रति मीटर या प्रमाणे 20 वर्षासाठी एकरक्कमी रु200/- प्रती मीटर प्रमाणे भुईभाडे",
          "quantity/pits": null,
          "length": null,
          "width": null,
          "area": null,
          "rate": null,
          "amount": 162400
        },
        {
          "sr_no": null,
          "type/description": "एकूण",
          "quantity/pits": null,
          "length": null,
          "width": null,
          "area": null,
          "rate": null,
          "amount": 15831241.0
        },
        {
          "sr_no": "1",
          "type/description": "नविन डांबरी पृष्ठभाग",
          "quantity/pits": 8.0,
          "length": 1.5,
          "width": 1.5,
          "area": 18.0,
          "rate": 9600.0,
          "amount": 172800.0
        },
        {
          "sr_no": null,
          "type/description": "डक्ट मधुन केबल",
          "quantity/pits": 0.0,
          "length": 0.0,
          "width": 0.0,
          "area": 0.0,
          "rate": 0.0,
          "amount": 0.0
        },
        {
          "sr_no": null,
          "type/description": "डक्ट ची संख्या 3",
          "quantity/pits": 0.0,
          "length": null,
          "width": null,
          "area": 812.0,
          "rate": 0.0,
          "amount": 2436.0
        },
        {
          "sr_no": "1",
          "type/description": "नविन डांबरी पृष्ठभाग (ओपन ट्रेंच पध्दत)",
          "quantity/pits": 0.0,
          "length": 0.0,
          "width": 0.0,
          "area": 627.0,
          "rate": 9600.0,
          "amount": 6019200.0
        },
        {
          "sr_no": null,
          "type/description": "पुनःस्थापना शुल्क",
          "quantity/pits": null,
          "length": null,
          "width": null,
          "area": null,
          "rate": null,
          "amount": 12386436.0
        },
        {
          "sr_no": "A",
          "type/description": "A वर पर्यवेक्षण शुल्क १५ %",
          "quantity/pits": null,
          "length": null,
          "width": null,
          "area": null,
          "rate": null,
          "amount": 1857965.0
        },
        {
          "sr_no": "B",
          "type/description": "A+B वर सुरक्षा अनामत रक्कम १०%",
          "quantity/pits": null,
          "length": null,
          "width": null,
          "area": null,
          "rate": null,
          "amount": 1424440.0
        },
        {
          "sr_no": "D",
          "type/description": "रु १०/- प्रति वर्ष प्रति मीटर या प्रमाणे 20 वर्षासाठी एकरक्कमी रु200/- प्रती मीटर प्रमाणे भुईभाडे",
          "quantity/pits": null,
          "length": null,
          "width": null,
          "area": null,
          "rate": null,
          "amount": 162400.0
        },
        {
          "sr_no": null,
          "type/description": "एकूण",
          "quantity/pits": null,
          "length": null,
          "width": null,
          "area": null,
          "rate": null,
          "amount": 15831241.0
        }
      ],
      "summary": {}
    }
  ]
}